{"material":"player_head","durability":3,"skin":"eyJ0ZXh0dXJlcyI6eyJTS0lOIjp7InVybCI6Imh0dHA6Ly90ZXh0dXJlcy5taW5lY3JhZnQubmV0L3RleHR1cmUvMTk0MjIxYTBkZTkzNmJhYzVjZTg5NWYyYWNhZDE5YzY0Nzk1YzE4Y2U1NTU1Yjk3MTU5NDIwNWJkM2VjIn19fQ==","name":{"text":"Cheap Coffee"},"unstackable":true,"id":"CHEAP_COFFEE","description":[{"color":"dark_gray","text":"Basic Brew"},{"text":""},{"color":"gray","text":"Use this item in place of"},{"color":"gray","text":"an Awkward Potion for"},{"color":"gray","text":"certain potions."},{"text":""},{"extra":[{"color":"gray","text":"Adds "},{"color":"white","text":"+5✦ Speed "},{"color":"gray","text":"to potions"}],"text":""},{"color":"gray","text":"with that stat."},{"text":""},{"extra":[{"bold":true,"color":"white","text":"COMMON"},{"color":"white","text":""}],"text":""}],"tier":"common"}