{"material":"GOLDEN_AXE","name":{"text":"Daedalus Axe"},"category":"SWORD","sword_type":"AXE","tier":"legendary","gemstone_slots":[{"slot_type":"COMBAT","costs":[{"type":"COINS","coins":50000},{"type":"ITEM","item_id":"FINE_JASPER_GEM","amount":20},{"type":"ITEM","item_id":"FINE_SAPPHIRE_GEM","amount":20},{"type":"ITEM","item_id":"FINE_RUBY_GEM","amount":20},{"type":"ITEM","item_id":"FINE_AMETHYST_GEM","amount":20}]},{"slot_type":"COMBAT","costs":[{"type":"COINS","coins":100000},{"type":"ITEM","item_id":"FINE_JASPER_GEM","amount":40},{"type":"ITEM","item_id":"FINE_SAPPHIRE_GEM","amount":40},{"type":"ITEM","item_id":"FINE_RUBY_GEM","amount":40},{"type":"ITEM","item_id":"FINE_AMETHYST_GEM","amount":40}]}],"id":"DAEDALUS_AXE","can_be_reforged":true,"description":[{"color":"dark_gray","text":"  [⚔] [⚔]"},{"text":""},{"extra":[{"color":"gray","text":"Gains "},{"color":"red","text":"+4 Damage "},{"color":"gray","text":"per Taming"}],"text":""},{"color":"gray","text":"level."},{"color":"gray","text":"Copies the stats from your"},{"color":"gray","text":"active pet."},{"text":""},{"extra":[{"color":"gray","text":"Earn "},{"color":"gold","text":"+35 coins "},{"color":"gray","text":"from"}],"text":""},{"color":"gray","text":"monster kills"},{"text":""},{"extra":[{"color":"gray","text":"Deals "},{"color":"green","text":"+200% "},{"color":"gray","text":"damage against"}],"text":""},{"color":"gray","text":"mythological creatures and Minos"},{"color":"gray","text":"followers"},{"text":""},{"color":"dark_gray","text":"This item can be reforged!"},{"extra":[{"bold":true,"color":"gold","text":"LEGENDARY SWORD"},{"color":"gold","text":" "}],"text":""}]}