{"material":"enchanted_book","id":"enchantment_rend_4","tier":"common","name":{"text":"Enchanted Book"},"description":[{"color":"blue","text":"Rend 4"},{"color":"gray","text":"Use Left Click ability to rip "},{"color":"gray","text":"your arrows out of nearby "},{"extra":[{"color":"gray","text":"enemies. Each arrow deals "},{"color":"red","text":"20% "}],"text":""},{"color":"gray","text":"of your last critical shot on "},{"extra":[{"color":"gray","text":"the target, up to "},{"color":"red","text":"5 "},{"color":"gray","text":"arrows. "}],"text":""},{"extra":[{"color":"green","text":"2s "},{"color":"gray","text":"Cooldown"}],"text":""},{"text":""},{"color":"gray","text":"Use this on an item in an Anvil"},{"color":"gray","text":"to apply it!"},{"text":""},{"bold":true,"color":"white","text":"COMMON"}]}