{"material":"player_head","skin_url":"https://textures.minecraft.net/texture/01433be242366af126da434b8735df1eb5b3cb2cede39145974e9c483607bac","id":"pet_squid_uncommon","tier":"UNCOMMON","name":{"extra":[{"color":"gray","text":"[Lvl 100] "},{"color":"green","text":"Squid"}],"text":""},"description":[{"color":"dark_gray","text":"Fishing Pet"},{"text":""},{"extra":[{"color":"gray","text":"Intelligence: "},{"color":"green","text":"+50"}],"text":""},{"extra":[{"color":"gray","text":"Health: "},{"color":"green","text":"+50"}],"text":""},{"text":""},{"color":"gold","text":"More Ink"},{"extra":[{"color":"gray","text":"Gain a "},{"color":"green","text":"75% "},{"color":"gray","text":"chance to get"}],"text":""},{"color":"gray","text":"double drops from squids."},{"text":""},{"extra":[{"bold":true,"color":"green","text":"UNCOMMON"},{"color":"green","text":""}],"text":""}]}