{
  "material": "cod",
  "name": "Fishing Exp Boost",
  "glowing": true,
  "category": "PET_ITEM",
  "tier": "EPIC",
  "id": "PET_ITEM_FISHING_SKILL_BOOST_EPIC",
  "description": [
    {
      "color": "dark_gray",
      "text": "Consumed on use"
    },
    {
      "text": ""
    },
    {
      "color": "gray",
      "text": "Pet items can boost pets in"
    },
    {
      "color": "gray",
      "text": "various ways but pets can only"
    },
    {
      "color": "gray",
      "text": "hold 1 item at a time so choose"
    },
    {
      "color": "gray",
      "text": "wisely!"
    },
    {
      "text": ""
    },
    {
      "extra": [
        {
          "color": "gray",
          "text": "Gives +"
        },
        {
          "color": "green",
          "text": "50% "
        },
        {
          "color": "gray",
          "text": "pet exp for"
        }
      ],
      "text": ""
    },
    {
      "color": "gray",
      "text": "Fishing."
    },
    {
      "text": ""
    },
    {
      "color": "yellow",
      "text": "Right click on your summoned"
    },
    {
      "color": "yellow",
      "text": "pet to give it this item!"
    },
    {
      "text": ""
    }
  ]
}