{
  "material": "LEATHER_LEGGINGS",
  "color": "0,44,166",
  "name": "Shark Scale Leggings",
  "category": "LEGGINGS",
  "tier": "LEGENDARY",
  "stats": {
    "DEFENSE": 150,
    "HEALTH": 150
  },
  "npc_sell_price": 56000,
  "requirements": [
    {
      "type": "SKILL",
      "skill": "FISHING",
      "level": 24
    }
  ],
  "gemstone_slots": [
    {
      "slot_type": "AMETHYST"
    },
    {
      "slot_type": "AMETHYST"
    }
  ],
  "id": "SHARK_SCALE_LEGGINGS",
  "can_be_reforged": true,
  "description": [
    {
      "text": ""
    },
    {
      "color": "gold",
      "text": "Full Set Bonus: Absorb"
    },
    {
      "extra": [
        {
          "color": "blue",
          "text": "Doubles"
        },
        {
          "color": "gray",
          "text": " your "
        },
        {
          "color": "green",
          "text": "\u2748 Defense"
        },
        {
          "color": "gray",
          "text": ""
        }
      ],
      "text": ""
    },
    {
      "color": "gray",
      "text": "while in water."
    },
    {
      "text": ""
    },
    {
      "color": "gold",
      "text": "Full Set Bonus: Reflect"
    },
    {
      "color": "gray",
      "text": "Your sharp scales reflect"
    },
    {
      "extra": [
        {
          "color": "blue",
          "text": "15% "
        },
        {
          "color": "gray",
          "text": "of damage onto the"
        }
      ],
      "text": ""
    },
    {
      "color": "gray",
      "text": "attacker."
    },
    {
      "text": ""
    }
  ]
}