{"material":"bow","id":"starred_item_spirit_bow","tier":"legendary","name":{"text":"⚚ Spirit Shortbow"},"description":[{"extra":[{"color":"gray","text":"Gear Score: "},{"color":"light_purple","text":"370 "}],"text":""},{"extra":[{"color":"gray","text":"Damage: "},{"color":"red","text":"+220 "}],"text":""},{"extra":[{"color":"gray","text":"Strength: "},{"color":"red","text":"+110 "}],"text":""},{"extra":[{"color":"gray","text":"Shot Cooldown: "},{"color":"green","text":"0.7s"}],"text":""},{"text":""},{"extra":[{"color":"gray","text":"Deals "},{"color":"green","text":"+2% "},{"color":"gray","text":"damage to "},{"color":"green","text":"Undead"}],"text":""},{"extra":[{"color":"green","text":"monsters "},{"color":"gray","text":"for every "},{"color":"green","text":"1% "},{"color":"gray","text":"of"}],"text":""},{"color":"gray","text":"your missing health."},{"text":""},{"extra":[{"color":"aqua","text":"Spirit Item: "},{"color":"gray","text":"When turned"}],"text":""},{"color":"gray","text":"into a ghost, this item becomes"},{"color":"gray","text":"a Ghost Ability."},{"text":""},{"color":"gold","text":"Spirit Ability: Spirit Bomb "},{"color":"gray","text":"Shoots a spirit that deals"},{"extra":[{"color":"red","text":"8000 "},{"color":"gray","text":"damage on impact."}],"text":""},{"text":""},{"color":"gold","text":"Shortbow: Instantly shoots!"},{"text":""},{"color":"dark_gray","text":"This item can be reforged!"},{"extra":[{"color":"dark_red","text":"❣ "},{"color":"red","text":"Requires "},{"color":"green","text":"The Catacombs Floor"}],"text":""},{"extra":[{"color":"green","text":"IV Completion"},{"color":"red","text":"."}],"text":""},{"extra":[{"bold":true,"color":"gold","text":"LEGENDARY DUNGEON BOW"},{"color":"gold","text":""}],"text":""}]}