{"material":"GLOWSTONE_DUST","name":{"text":"Sulphur"},"description":[{"extra":[{"italic":true,"color":"gray","text":"\"Give me some Sulphur and"},{"color":"gray","text":""}],"text":""},{"extra":[{"italic":true,"color":"gray","text":"I'll make a wand. Give me all"},{"color":"gray","text":""}],"text":""},{"extra":[{"italic":true,"color":"gray","text":"the Sulphur and I'll conquer the"},{"color":"gray","text":""}],"text":""},{"extra":[{"italic":true,"color":"gray","text":"world.\" - Unnamed Mage."},{"color":"gray","text":""}],"text":""},{"text":""},{"extra":[{"bold":true,"color":"green","text":"UNCOMMON"},{"color":"green","text":""}],"text":""}],"tier":"uncommon","npc_sell_price":10,"id":"SULPHUR_ORE"}