{
  "material": "LEATHER_CHESTPLATE",
  "color": "90,100,100",
  "name": "Super Heavy Chestplate",
  "category": "CHESTPLATE",
  "tier": "EPIC",
  "npc_sell_price": 1,
  "tiered_stats": {
    "WALK_SPEED": [
      -10,
      -10,
      -10,
      -10,
      -10,
      -10,
      -10,
      -10,
      -10,
      -10
    ],
    "DEFENSE": [
      112,
      124,
      139,
      154,
      171,
      190,
      211,
      234,
      261,
      290
    ]
  },
  "upgrade_costs": [
    [
      {
        "type": "ESSENCE",
        "essence_type": "UNDEAD",
        "amount": 25
      }
    ],
    [
      {
        "type": "ESSENCE",
        "essence_type": "UNDEAD",
        "amount": 50
      }
    ],
    [
      {
        "type": "ESSENCE",
        "essence_type": "UNDEAD",
        "amount": 100
      }
    ],
    [
      {
        "type": "ESSENCE",
        "essence_type": "UNDEAD",
        "amount": 200
      }
    ],
    [
      {
        "type": "ESSENCE",
        "essence_type": "UNDEAD",
        "amount": 400
      }
    ]
  ],
  "gear_score": 10,
  "requirements": [
    {
      "type": "DUNGEON_SKILL",
      "dungeon_type": "CATACOMBS",
      "level": 15
    }
  ],
  "dungeon_item": true,
  "id": "SUPER_HEAVY_CHESTPLATE",
  "can_be_reforged": true,
  "description": [
    {
      "text": ""
    },
    {
      "color": "gray",
      "text": "Each piece of this armor reduces"
    },
    {
      "extra": [
        {
          "color": "gray",
          "text": "the cooldown of "
        },
        {
          "color": "blue",
          "text": "Seismic Wave"
        }
      ],
      "text": ""
    },
    {
      "extra": [
        {
          "color": "gray",
          "text": "by "
        },
        {
          "color": "green",
          "text": "1s"
        },
        {
          "color": "gray",
          "text": "."
        }
      ],
      "text": ""
    },
    {
      "text": ""
    },
    {
      "color": "gold",
      "text": "Full Set Bonus: Vindicate"
    },
    {
      "extra": [
        {
          "color": "gray",
          "text": "Grants "
        },
        {
          "color": "white",
          "text": "+1 walk speed "
        },
        {
          "color": "gray",
          "text": "for"
        }
      ],
      "text": ""
    },
    {
      "extra": [
        {
          "color": "gray",
          "text": "every "
        },
        {
          "color": "green",
          "text": "50 "
        },
        {
          "color": "gray",
          "text": "defense that you"
        }
      ],
      "text": ""
    },
    {
      "color": "gray",
      "text": "have."
    },
    {
      "text": ""
    },
    {
      "color": "green",
      "text": "Perfect 52500 / 52500"
    }
  ]
}