{
  "material": "LEATHER_HELMET",
  "color": "230,230,230",
  "name": "Super Heavy Helmet",
  "category": "HELMET",
  "tier": "EPIC",
  "npc_sell_price": 1,
  "tiered_stats": {
    "WALK_SPEED": [
      -10,
      -10,
      -10,
      -10,
      -10,
      -10,
      -10,
      -10,
      -10,
      -10
    ],
    "DEFENSE": [
      70,
      78,
      86,
      96,
      106,
      118,
      131,
      146,
      162,
      180
    ]
  },
  "upgrade_costs": [
    [
      {
        "type": "ESSENCE",
        "essence_type": "UNDEAD",
        "amount": 25
      }
    ],
    [
      {
        "type": "ESSENCE",
        "essence_type": "UNDEAD",
        "amount": 50
      }
    ],
    [
      {
        "type": "ESSENCE",
        "essence_type": "UNDEAD",
        "amount": 100
      }
    ],
    [
      {
        "type": "ESSENCE",
        "essence_type": "UNDEAD",
        "amount": 200
      }
    ],
    [
      {
        "type": "ESSENCE",
        "essence_type": "UNDEAD",
        "amount": 400
      }
    ]
  ],
  "gear_score": 10,
  "requirements": [
    {
      "type": "DUNGEON_SKILL",
      "dungeon_type": "CATACOMBS",
      "level": 15
    }
  ],
  "dungeon_item": true,
  "id": "SUPER_HEAVY_HELMET"
}