{"material":"STICK","name":{"text":"Tribal Spear"},"category":"SWORD","tier":"rare","stats":{"STRENGTH":100},"id":"TRIBAL_SPEAR","can_be_reforged":true,"description":[{"extra":[{"color":"gray","text":"Strength: "},{"color":"red","text":"+100"}],"text":""},{"text":""},{"extra":[{"color":"gold","text":"Ability: Thwack "},{"bold":true,"color":"yellow","text":"RIGHT CLICK"},{"color":"gold","text":""}],"text":""},{"color":"gray","text":"Throw the spear like an arrow"},{"color":"gray","text":"which will return to you."},{"text":""},{"color":"dark_gray","text":"This item can be reforged!"},{"extra":[{"bold":true,"color":"blue","text":"RARE SWORD"},{"color":"blue","text":""}],"text":""}]}