{"material":"player_head","durability":3,"skin":"eyJ0ZXh0dXJlcyI6eyJTS0lOIjp7InVybCI6Imh0dHA6Ly90ZXh0dXJlcy5taW5lY3JhZnQubmV0L3RleHR1cmUvOWQwNmQ5YTA0YTVhNzcyMDYxNGU5MzRjNzVjNmI2NTFmMGViYWJlYTNhNzQ2MWYxYzc0MTA1YzdhMmEwZTY3MiJ9fX0=","name":{"text":"Vampire Dentist Relic"},"tier":"legendary","category":"ACCESSORY","origin":"RIFT","npc_sell_price":80000,"rift_transferrable":true,"stats":{"health_regeneration":10,"vitality":1,"rift_time":30,"rift_health":1},"item_specific":{"cooldown_seconds":1,"bonus_heal":1},"id":"VAMPIRE_DENTIST_RELIC","description":[{"extra":[{"color":"gray","text":"Health Regen: "},{"color":"green","text":"+10"}],"text":""},{"extra":[{"color":"gray","text":"Vitality: "},{"color":"green","text":"+1"}],"text":""},{"text":""},{"color":"gray","text":"Apply a natural regen tick when"},{"extra":[{"color":"gray","text":"you deal melee damage. "},{"color":"dark_gray","text":"(0.5s"}],"text":""},{"color":"dark_gray","text":"cooldown)"},{"text":""},{"extra":[{"color":"dark_purple","text":"X"},{"color":"dark_purple","text":" Rift-Transferable X"}],"text":""},{"extra":[{"bold":true,"color":"gold","text":"LEGENDARY ACCESSORY"},{"color":"gold","text":""}],"text":""}]}