{
  "material": "IRON_SWORD",
  "name": "Zombie Knight Sword",
  "category": "SWORD",
  "tier": "EPIC",
  "npc_sell_price": 1,
  "tiered_stats": {
    "DAMAGE": [
      82,
      86,
      91,
      95,
      101,
      106,
      111,
      117,
      123,
      130
    ],
    "STRENGTH": [
      21,
      22,
      24,
      26,
      28,
      30,
      32,
      36,
      37,
      40
    ]
  },
  "upgrade_costs": [
    [
      {
        "type": "ESSENCE",
        "essence_type": "UNDEAD",
        "amount": 20
      }
    ],
    [
      {
        "type": "ESSENCE",
        "essence_type": "UNDEAD",
        "amount": 40
      }
    ],
    [
      {
        "type": "ESSENCE",
        "essence_type": "UNDEAD",
        "amount": 80
      }
    ],
    [
      {
        "type": "ESSENCE",
        "essence_type": "UNDEAD",
        "amount": 160
      }
    ],
    [
      {
        "type": "ESSENCE",
        "essence_type": "UNDEAD",
        "amount": 320
      }
    ]
  ],
  "gear_score": 20,
  "requirements": [
    {
      "type": "DUNGEON_SKILL",
      "dungeon_type": "CATACOMBS",
      "level": 14
    }
  ],
  "dungeon_item": true,
  "id": "ZOMBIE_KNIGHT_SWORD",
  "can_be_reforged": true,
  "description": [
    {
      "text": ""
    },
    {
      "color": "gold",
      "text": "Full Set Bonus: Zombie Knight"
    },
    {
      "extra": [
        {
          "color": "gray",
          "text": "Gains "
        },
        {
          "color": "red",
          "text": "+30\u2741 "
        },
        {
          "color": "gray",
          "text": "Strength when"
        }
      ],
      "text": ""
    },
    {
      "color": "gray",
      "text": "used with the Zombie Knight"
    },
    {
      "color": "gray",
      "text": "Armor"
    },
    {
      "text": ""
    },
    {
      "color": "green",
      "text": "Perfect 52500 / 52500"
    }
  ]
}